nautobot_prometheus_sd/__init__.py
nautobot_prometheus_sd/api/__init__.py
nautobot_prometheus_sd/api/serializers.py
nautobot_prometheus_sd/api/urls.py
nautobot_prometheus_sd/api/utils.py
nautobot_prometheus_sd/api/views.py
nautobot_prometheus_sd/filters.py
nautobot_prometheus_sd/tests/__init__.py
nautobot_prometheus_sd/tests/test_api.py
nautobot_prometheus_sd/tests/test_serializers.py
nautobot_prometheus_sd/tests/utils.py
nautobot_prometheus_sd-2.4.13.dist-info/LICENSE
nautobot_prometheus_sd-2.4.13.dist-info/METADATA
nautobot_prometheus_sd-2.4.13.dist-info/WHEEL
nautobot_prometheus_sd-2.4.13.dist-info/RECORD
