Metadata-Version: 2.1
Name: nautobot-prometheus-sd
Version: 2.4.13
Summary: A Nautobot plugin to provide Netbox entires to Prometheus HTTP service discovery
License: MIT
Author: Felix Peters
Author-email: felix.peters@breuninger.de
Requires-Python: >=3.9.2,<3.13
Classifier: License :: OSI Approved :: MIT License
Classifier: Programming Language :: Python :: 3
Classifier: Programming Language :: Python :: 3.10
Classifier: Programming Language :: Python :: 3.11
Classifier: Programming Language :: Python :: 3.12
Provides-Extra: all
Requires-Dist: nautobot (>=2.1.0,<3.0.0)
Requires-Dist: pre-commit (>=4.2.0,<5.0.0)
